{"Andhra Pradesh": {"19/03/2020 06:14": ["1", "0", "0", "0"], "latest": ["1", "0", "0", "0"]}, "Delhi": {"19/03/2020 06:14": ["11", "1", "2", "1"], "latest": ["11", "1", "2", "1"]}, "Haryana": {"19/03/2020 06:14": ["3", "14", "0", "0"], "latest": ["3", "14", "0", "0"]}, "Karnataka": {"19/03/2020 06:14": ["14", "0", "0", "1"], "latest": ["14", "0", "0", "1"]}, "Kerala": {"19/03/2020 06:14": ["25", "2", "3", "0"], "latest": ["25", "2", "3", "0"]}, "Maharashtra": {"19/03/2020 06:14": ["42", "3", "0", "1"], "latest": ["42", "3", "0", "1"]}, "Odisha": {"19/03/2020 06:14": ["1", "0", "0", "0"], "latest": ["1", "0", "0", "0"]}, "Pondicherry": {"19/03/2020 06:14": ["1", "0", "0", "0"], "latest": ["1", "0", "0", "0"]}, "Punjab": {"19/03/2020 06:14": ["1", "0", "0", "0"], "latest": ["1", "0", "0", "0"]}, "Rajasthan": {"19/03/2020 06:14": ["5", "2", "3", "0"], "latest": ["5", "2", "3", "0"]}, "Tamil Nadu": {"19/03/2020 06:14": ["2", "0", "1", "0"], "latest": ["2", "0", "1", "0"]}, "Telengana": {"19/03/2020 06:14": ["4", "2", "1", "0"], "latest": ["4", "2", "1", "0"]}, "Union Territory of Chandigarh": {"19/03/2020 06:14": ["1", "0", "0", "0"], "latest": ["1", "0", "0", "0"]}, "Union Territory of Jammu and Kashmir": {"19/03/2020 06:14": ["4", "0", "0", "0"], "latest": ["4", "0", "0", "0"]}, "Union Territory of Ladakh": {"19/03/2020 06:14": ["8", "0", "0", "0"], "latest": ["8", "0", "0", "0"]}, "Uttar Pradesh": {"19/03/2020 06:14": ["16", "1", "5", "0"], "latest": ["16", "1", "5", "0"]}, "Uttarakhand": {"19/03/2020 06:14": ["1", "0", "0", "0"], "latest": ["1", "0", "0", "0"]}, "West Bengal": {"19/03/2020 06:14": ["1", "0", "0", "0"], "latest": ["1", "0", "0", "0"]}, "Total number of confirmed cases in India": {"19/03/2020 06:14": ["141", "25", "15", "3"], "latest": ["141", "25", "15", "3"]}, "1": {"latest": ["Andaman and Nicobar Islands", "33", "33", "0"], "26/05/2020 18:50": ["Andaman and Nicobar Islands", "33", "33", "0"], "27/05/2020 00:39": ["Andaman and Nicobar Islands", "33", "33", "0"], "27/05/2020 13:09": ["Andaman and Nicobar Islands", "33", "33", "0"], "28/05/2020 19:32": ["Andaman and Nicobar Islands", "33", "33", "0"]}, "2": {"latest": ["Andhra Pradesh", "3171", "2057", "58"], "26/05/2020 18:50": ["Andhra Pradesh", "3110", "1896", "56"], "27/05/2020 00:39": ["Andhra Pradesh", "3110", "1896", "56"], "27/05/2020 13:09": ["Andhra Pradesh", "3171", "2009", "57"], "28/05/2020 19:32": ["Andhra Pradesh", "3171", "2057", "58"]}, "3": {"latest": ["Arunachal Pradesh", "2", "1", "0"], "26/05/2020 18:50": ["Arunachal Pradesh", "2", "1", "0"], "27/05/2020 00:39": ["Arunachal Pradesh", "2", "1", "0"], "27/05/2020 13:09": ["Arunachal Pradesh", "2", "1", "0"], "28/05/2020 19:32": ["Arunachal Pradesh", "2", "1", "0"]}, "4": {"latest": ["Assam", "781", "87", "4"], "26/05/2020 18:50": ["Assam", "526", "62", "4"], "27/05/2020 00:39": ["Assam", "526", "62", "4"], "27/05/2020 13:09": ["Assam", "616", "62", "4"], "28/05/2020 19:32": ["Assam", "781", "87", "4"]}, "5": {"latest": ["Bihar", "3061", "1083", "15"], "26/05/2020 18:50": ["Bihar", "2729", "749", "13"], "27/05/2020 00:39": ["Bihar", "2730", "749", "13"], "27/05/2020 13:09": ["Bihar", "2983", "900", "13"], "28/05/2020 19:32": ["Bihar", "3061", "1083", "15"]}, "6": {"latest": ["Chandigarh", "279", "187", "4"], "26/05/2020 18:50": ["Chandigarh", "238", "186", "3"], "27/05/2020 00:39": ["Chandigarh", "238", "186", "3"], "27/05/2020 13:09": ["Chandigarh", "266", "187", "4"], "28/05/2020 19:32": ["Chandigarh", "279", "187", "4"]}, "7": {"latest": ["Chhattisgarh", "369", "83", "0"], "26/05/2020 18:50": ["Chhattisgarh", "291", "72", "0"], "27/05/2020 00:39": ["Chhattisgarh", "291", "72", "0"], "27/05/2020 13:09": ["Chhattisgarh", "361", "79", "0"], "28/05/2020 19:32": ["Chhattisgarh", "369", "83", "0"]}, "8": {"latest": ["Dadar Nagar Haveli", "2", "0", "0"], "26/05/2020 18:50": ["Dadar Nagar Haveli", "2", "0", "0"], "27/05/2020 00:39": ["Dadar Nagar Haveli", "2", "0", "0"], "27/05/2020 13:09": ["Dadar Nagar Haveli", "2", "0", "0"], "28/05/2020 19:32": ["Dadar Nagar Haveli", "2", "0", "0"]}, "9": {"latest": ["Delhi", "15257", "7264", "303"], "26/05/2020 18:50": ["Delhi", "14053", "6771", "276"], "27/05/2020 00:39": ["Delhi", "14053", "6771", "276"], "27/05/2020 13:09": ["Delhi", "14465", "7223", "288"], "28/05/2020 19:32": ["Delhi", "15257", "7264", "303"]}, "10": {"latest": ["Goa", "68", "37", "0"], "26/05/2020 18:50": ["Goa", "67", "19", "0"], "27/05/2020 00:39": ["Goa", "67", "19", "0"], "27/05/2020 13:09": ["Goa", "67", "28", "0"], "28/05/2020 19:32": ["Goa", "68", "37", "0"]}, "11": {"latest": ["Gujarat", "15195", "7549", "938"], "26/05/2020 18:50": ["Gujarat", "14460", "6636", "888"], "27/05/2020 00:39": ["Gujarat", "14460", "6636", "888"], "27/05/2020 13:09": ["Gujarat", "14821", "7139", "915"], "28/05/2020 19:32": ["Gujarat", "15195", "7549", "938"]}, "12": {"latest": ["Haryana", "1381", "838", "18"], "26/05/2020 18:50": ["Haryana", "1184", "765", "16"], "27/05/2020 00:39": ["Haryana", "1184", "765", "16"], "27/05/2020 13:09": ["Haryana", "1305", "824", "17"], "28/05/2020 19:32": ["Haryana", "1381", "838", "18"]}, "13": {"latest": ["Himachal Pradesh", "273", "70", "5"], "26/05/2020 18:50": ["Himachal Pradesh", "223", "67", "5"], "27/05/2020 00:39": ["Himachal Pradesh", "223", "67", "5"], "27/05/2020 13:09": ["Himachal Pradesh", "247", "67", "5"], "28/05/2020 19:32": ["Himachal Pradesh", "273", "70", "5"]}, "14": {"latest": ["Jammu and Kashmir", "1921", "854", "26"], "26/05/2020 18:50": ["Jammu and Kashmir", "1668", "809", "23"], "27/05/2020 00:39": ["Jammu and Kashmir", "1668", "809", "23"], "27/05/2020 13:09": ["Jammu and Kashmir", "1759", "833", "24"], "28/05/2020 19:32": ["Jammu and Kashmir", "1921", "854", "26"]}, "15": {"latest": ["Jharkhand", "448", "185", "4"], "26/05/2020 18:50": ["Jharkhand", "377", "148", "4"], "27/05/2020 00:39": ["Jharkhand", "377", "148", "4"], "27/05/2020 13:09": ["Jharkhand", "426", "175", "4"], "28/05/2020 19:32": ["Jharkhand", "448", "185", "4"]}, "16": {"latest": ["Karnataka", "2418", "781", "47"], "26/05/2020 18:50": ["Karnataka", "2182", "705", "44"], "27/05/2020 00:39": ["Karnataka", "2182", "705", "44"], "27/05/2020 13:09": ["Karnataka", "2283", "748", "44"], "28/05/2020 19:32": ["Karnataka", "2418", "781", "47"]}, "17": {"latest": ["Kerala", "1004", "552", "7"], "26/05/2020 18:50": ["Kerala", "896", "532", "5"], "27/05/2020 00:39": ["Kerala", "896", "532", "5"], "27/05/2020 13:09": ["Kerala", "963", "542", "6"], "28/05/2020 19:32": ["Kerala", "1004", "552", "7"]}, "18": {"latest": ["Ladakh", "53", "43", "0"], "26/05/2020 18:50": ["Ladakh", "52", "43", "0"], "27/05/2020 00:39": ["Ladakh", "52", "43", "0"], "27/05/2020 13:09": ["Ladakh", "53", "43", "0"], "28/05/2020 19:32": ["Ladakh", "53", "43", "0"]}, "19": {"latest": ["Madhya Pradesh", "7261", "3927", "313"], "26/05/2020 18:50": ["Madhya Pradesh", "6859", "3571", "300"], "27/05/2020 00:39": ["Madhya Pradesh", "6859", "3571", "300"], "27/05/2020 13:09": ["Madhya Pradesh", "7024", "3689", "305"], "28/05/2020 19:32": ["Madhya Pradesh", "7261", "3927", "313"]}, "20": {"latest": ["Maharashtra", "56948", "17918", "1897"], "26/05/2020 18:50": ["Maharashtra", "52667", "15786", "1695"], "27/05/2020 00:39": ["Maharashtra", "52667", "15786", "1695"], "27/05/2020 13:09": ["Maharashtra", "54758", "16954", "1792"], "28/05/2020 19:32": ["Maharashtra", "56948", "17918", "1897"]}, "21": {"latest": ["Manipur", "44", "4", "0"], "26/05/2020 18:50": ["Manipur", "39", "4", "0"], "27/05/2020 00:39": ["Manipur", "39", "4", "0"], "27/05/2020 13:09": ["Manipur", "39", "4", "0"], "28/05/2020 19:32": ["Manipur", "44", "4", "0"]}, "22": {"latest": ["Meghalaya", "20", "12", "1"], "26/05/2020 18:50": ["Meghalaya", "14", "12", "1"], "27/05/2020 00:39": ["Meghalaya", "14", "12", "1"], "27/05/2020 13:09": ["Meghalaya", "15", "12", "1"], "28/05/2020 19:32": ["Meghalaya", "20", "12", "1"]}, "23": {"latest": ["Mizoram", "1", "1", "0"], "26/05/2020 18:50": ["Mizoram", "1", "1", "0"], "27/05/2020 00:39": ["Mizoram", "1", "1", "0"], "27/05/2020 13:09": ["Mizoram", "1", "1", "0"], "28/05/2020 19:32": ["Mizoram", "1", "1", "0"]}, "24": {"latest": ["Nagaland", "4", "0", "0"], "26/05/2020 18:50": ["Nagaland", "3", "0", "0"], "27/05/2020 00:39": ["Nagaland", "3", "0", "0"], "27/05/2020 13:09": ["Nagaland", "4", "0", "0"], "28/05/2020 19:32": ["Nagaland", "4", "0", "0"]}, "25": {"latest": ["Odisha", "1593", "733", "7"], "26/05/2020 18:50": ["Odisha", "1438", "649", "7"], "27/05/2020 00:39": ["Odisha", "1438", "649", "7"], "27/05/2020 13:09": ["Odisha", "1517", "733", "7"], "28/05/2020 19:32": ["Odisha", "1593", "733", "7"]}, "26": {"latest": ["Puducherry", "46", "12", "0"], "26/05/2020 18:50": ["Puducherry", "41", "12", "0"], "27/05/2020 00:39": ["Puducherry", "41", "12", "0"], "27/05/2020 13:09": ["Puducherry", "46", "12", "0"], "28/05/2020 19:32": ["Puducherry", "46", "12", "0"]}, "27": {"latest": ["Punjab", "2139", "1918", "40"], "26/05/2020 18:50": ["Punjab", "2060", "1898", "40"], "27/05/2020 00:39": ["Punjab", "2060", "1898", "40"], "27/05/2020 13:09": ["Punjab", "2106", "1918", "40"], "28/05/2020 19:32": ["Punjab", "2139", "1918", "40"]}, "28": {"latest": ["Rajasthan", "7703", "4457", "173"], "26/05/2020 18:50": ["Rajasthan", "7300", "3951", "167"], "27/05/2020 00:39": ["Rajasthan", "7300", "3951", "167"], "27/05/2020 13:09": ["Rajasthan", "7536", "4171", "170"], "28/05/2020 19:32": ["Rajasthan", "7703", "4457", "173"]}, "29": {"latest": ["Sikkim", "1", "0", "0"], "26/05/2020 18:50": ["Sikkim", "1", "0", "0"], "27/05/2020 00:39": ["Sikkim", "1", "0", "0"], "27/05/2020 13:09": ["Sikkim", "1", "0", "0"], "28/05/2020 19:32": ["Sikkim", "1", "0", "0"]}, "30": {"latest": ["Tamil Nadu", "18545", "9909", "133"], "26/05/2020 18:50": ["Tamil Nadu", "17082", "8731", "118"], "27/05/2020 00:39": ["Tamil Nadu", "17082", "8731", "118"], "27/05/2020 13:09": ["Tamil Nadu", "17728", "9342", "127"], "28/05/2020 19:32": ["Tamil Nadu", "18545", "9909", "133"]}, "31": {"latest": ["Telengana", "2098", "1284", "63"], "26/05/2020 18:50": ["Telengana", "1920", "1164", "56"], "27/05/2020 00:39": ["Telengana", "1920", "1164", "56"], "27/05/2020 13:09": ["Telengana", "1991", "1284", "57"], "28/05/2020 19:32": ["Telengana", "2098", "1284", "63"]}, "32": {"latest": ["Tripura", "230", "165", "0"], "26/05/2020 18:50": ["Tripura", "194", "165", "0"], "27/05/2020 00:39": ["Tripura", "194", "165", "0"], "27/05/2020 13:09": ["Tripura", "207", "165", "0"], "28/05/2020 19:32": ["Tripura", "230", "165", "0"]}, "33": {"latest": ["Uttarakhand", "469", "79", "4"], "26/05/2020 18:50": ["Uttarakhand", "349", "58", "3"], "27/05/2020 00:39": ["Uttarakhand", "349", "58", "3"], "27/05/2020 13:09": ["Uttarakhand", "401", "64", "4"], "28/05/2020 19:32": ["Uttarakhand", "469", "79", "4"]}, "34": {"latest": ["Uttar Pradesh", "6991", "3991", "182"], "26/05/2020 18:50": ["Uttar Pradesh", "6532", "3581", "165"], "27/05/2020 00:39": ["Uttar Pradesh", "6532", "3581", "165"], "27/05/2020 13:09": ["Uttar Pradesh", "6548", "3698", "170"], "28/05/2020 19:32": ["Uttar Pradesh", "6991", "3991", "182"]}, "35": {"latest": ["West Bengal", "4192", "1578", "289"], "26/05/2020 18:50": ["West Bengal", "3816", "1414", "278"], "27/05/2020 00:39": ["West Bengal", "3816", "1414", "278"], "27/05/2020 13:09": ["West Bengal", "4009", "1486", "283"], "28/05/2020 19:32": ["West Bengal", "4192", "1578", "289"]}, "": {"latest": ["Total#", "158333", "67692", "4531"], "26/05/2020 18:50": ["Total#", "145379", "60491", "4167"], "27/05/2020 00:39": ["Total#", "145380", "60491", "4167"], "27/05/2020 13:09": ["Total#", "151767", "64426", "4337"], "28/05/2020 19:32": ["Total#", "158333", "67692", "4531"]}}